{
  "process":{
    "version":"1.1"
  },
  "document":[
    {
      "text":[
        {
          "name":"main",
          "text-id":"main",
          "content":"\n\n\n\n\n\n\n\nWij gebruiken cookies\ndaskapital.nl maakt gebruik van cookies en vergelijkbare technieken van haar of derden om I) het gedrag van bezoekers vast te leggen en te analyseren om de websites en apps te verbeteren, II) om het mogelijk te maken content via social media te delen en III) om de inhoud van haar websites en advertenties beter af te stemmen op jouw interesses en IV) om informatie te verzamelen over jouw voorkeuren en de informatie toe te voegen aan jouw klantprofiel. Zo kunnen we jou ook buiten daskapital.nl relevante aanbiedingen doen. Als u verder surft accepteer je deze cookies en ga je akkoord met de verwerking van de (persoons)gegevens die met behulp van cookies kunnen worden verzameld en verwerkt voor de onder I) tot en met IV) genoemde doeleinden.\nVoor meer informatie over privacy, cookiebeleid en Disclaimer klik dan\n                    hier\n\n\n\n\n\n\nJa, door hier te klikken ga ik akkoord met de cookies\n                \n\n\n\n\n\n"
        }
      ],
      "section":[
        {
          "id":"s1",
          "name":"main",
          "processed-as":"english",
          "allowed-as":[
            "english"
          ],
          "text-id":"main",
          "head":8,
          "tail":29
        },
        {
          "id":"s2",
          "name":"main",
          "processed-as":"english",
          "allowed-as":[
            "english"
          ],
          "text-id":"main",
          "head":30,
          "tail":848
        },
        {
          "id":"s3",
          "name":"main",
          "processed-as":"english",
          "allowed-as":[
            "english"
          ],
          "text-id":"main",
          "head":869,
          "tail":873
        },
        {
          "id":"s4",
          "name":"main",
          "processed-as":"english",
          "allowed-as":[
            "english"
          ],
          "text-id":"main",
          "head":880,
          "tail":933
        }
      ],
      "entity":[
        {
          "ontology":"entity:artifact:vehicle:ground",
          "value":"de verwerking van",
          "norm":"van",
          "id":"id1",
          "value-type":"descriptor",
          "resolve":"van",
          "value-rank":20,
          "entity-value":[
            {
              "type":"descriptor",
              "value":"de verwerking van",
              "script":"latin"
            }
          ],
          "entity-mention":[
            {
              "type":"descriptor",
              "value":"de verwerking van",
              "section":"main",
              "section-id":"s2",
              "text-id":"main",
              "head":622,
              "tail":639
            }
          ]
        },
        {
          "ontology":"entity:person",
          "value":"verder surft accepteer",
          "norm":"Verder Surft Accepteer",
          "id":"id3",
          "value-type":"name",
          "resolve":"verder_surft_accepteer",
          "value-rank":50,
          "entity-value":[
            {
              "type":"name",
              "value":"verder surft accepteer",
              "script":"latin"
            }
          ],
          "property":[
            {
              "name":"firstname",
              "value":"verder"
            },
            {
              "name":"middlename",
              "value":"surft"
            },
            {
              "name":"lastname",
              "value":"accepteer"
            },
            {
              "name":"gender",
              "value":"male"
            }
          ],
          "entity-mention":[
            {
              "type":"name",
              "value":"verder surft accepteer",
              "section":"main",
              "section-id":"s2",
              "text-id":"main",
              "head":562,
              "tail":584,
              "property":[
                {
                  "name":"firstname",
                  "value":"verder"
                },
                {
                  "name":"middlename",
                  "value":"surft"
                },
                {
                  "name":"lastname",
                  "value":"accepteer"
                },
                {
                  "name":"gender",
                  "value":"male"
                }
              ],
              "score":[
                {
                  "type":"confidence",
                  "value":3
                }
              ]
            }
          ]
        },
        {
          "ontology":"entity:person",
          "value":"Voor meer informatie",
          "norm":"Voor Meer Informatie",
          "id":"id5",
          "value-type":"name",
          "resolve":"voor_meer_informatie",
          "value-rank":50,
          "entity-value":[
            {
              "type":"name",
              "value":"Voor meer informatie",
              "script":"latin"
            }
          ],
          "property":[
            {
              "name":"firstname",
              "value":"voor_meer"
            },
            {
              "name":"lastname",
              "value":"informatie"
            },
            {
              "name":"gender",
              "value":"male"
            }
          ],
          "entity-mention":[
            {
              "type":"name",
              "value":"Voor meer informatie",
              "section":"main",
              "section-id":"s2",
              "text-id":"main",
              "head":778,
              "tail":798,
              "property":[
                {
                  "name":"firstname",
                  "value":"voor_meer"
                },
                {
                  "name":"lastname",
                  "value":"informatie"
                },
                {
                  "name":"gender",
                  "value":"male"
                }
              ],
              "score":[
                {
                  "type":"confidence",
                  "value":3
                }
              ]
            }
          ]
        },
        {
          "ontology":"entity:person",
          "value":"worden verzameld",
          "norm":"Worden Verzameld",
          "id":"id7",
          "value-type":"name",
          "resolve":"worden_verzameld",
          "value-rank":50,
          "entity-value":[
            {
              "type":"name",
              "value":"worden verzameld",
              "script":"latin"
            }
          ],
          "property":[
            {
              "name":"firstname",
              "value":"worden"
            },
            {
              "name":"lastname",
              "value":"verzameld"
            },
            {
              "name":"gender",
              "value":"male"
            }
          ],
          "entity-mention":[
            {
              "type":"name",
              "value":"worden verzameld",
              "section":"main",
              "section-id":"s2",
              "text-id":"main",
              "head":696,
              "tail":712,
              "property":[
                {
                  "name":"firstname",
                  "value":"worden"
                },
                {
                  "name":"lastname",
                  "value":"verzameld"
                },
                {
                  "name":"gender",
                  "value":"male"
                }
              ],
              "score":[
                {
                  "type":"confidence",
                  "value":3
                }
              ]
            }
          ]
        }
      ]
    }
  ]
}