{
  "process":{
    "version":"1.1"
  },
  "document":[
    {
      "text":[
        {
          "name":"main",
          "text-id":"main",
          "content":"\n\n\n  \n\n\n\nSkip to main content\n\n\n\n\n \n\n\n\n\n\n\n\nUser menu\n\n\nAbout FAS\nContact Us\n\n\n\n\n\nSite Search\n\n\nEnter your keywords \n\n\n\n\n\n \n\n \n \n\n\n\n\n\n\nUSDA United States Department of Agriculture Foreign Agricultural Service\n\n\n\n\n\n\n\n\n\n\nMain menuHome\nTopics\nCommodities & Products\nCountries & Regions\nData & Analysis\nPrograms\nNewsroom\n \n\n\n\n\n\n\n\n\n\n\n\n\n\n\n\n\n \n\n \n \n\n\n\n\n\n \n\nYou are here:HomeData & AnalysisUkraine: Grain and Feed Annual \n\n\n \n\n \n\nUkraine: Grain and Feed Annual\n\n\n \n\r\n    April 19, 2018  \n\n\n\n\nAttach Reports (GAIN) \n\n\n\n  \n\n\r\n    Commodities  \n\nGrain and Feed, Barley, Corn, Rye, Wheat \n\n\n  \n\n\r\n    Locations  \n\nEurope and Eurasia, Ukraine \n\n\n \n\n\nMY2018/19 wheat and barley production volumes are forecast to remain relatively stable, with corn increasing slightly and rye decreasing. Due to unique weather conditions as well as changes to support policy, summer crop areas might face some uncertainty. Ukraine will remain an active grain exporter with Black Sea ports remaining the export gateway for grains. Wheat flour exports are growing for the fourth year in a row.\nUkraine: Grain and Feed Annual\n\n\n \n\r\n      Contact    \n\n\n\n\n\r\n    Office of Agricultural Affairs, Kyiv  \n\r\n    (011-380-44) 521-5496  \n \n \n\n\n\r\n      Recent Attach Reports (GAIN)    \n\n\n\n \nInfographic: USMCA - Strengthening Ties with Our North American NeighborsJune 27, 2019Infographic looking at the agricultural trade between the U.S., Mexico and Canada.  The U.S. exported nearly $40 billion in agriculture to these two countries in 2018.\n\n \nUkraine: Grain and Feed UpdateJune 25, 2019This report contains FAS Kyivs revised production forecasts for MY2019/20 as well as trade estimates for MY2018/19. \n\n\n\nView More Data & Analysis \n \n\n\n\n\n\nInsight and analysis from FAS's overseas offices on issues affecting agricultural production and trade.\n\n\n\n\n\n\n\n\n\n\n\n\n\n\n\n\n\nStay Connected\n\nTwitter\nGovDelivery\nRSS\nFacebook\nYouTube\nFlickr\n \n\n\n\nFAS on Twitter\n\nTweets by @USDAForeignAg \n\n\n\nGet Email Updates\n\n\n\n\n\n\n\n \n\n \n\n\n\n\n\n\n\nInternational Travel\nAccessibility Statement\nEconomic Research Service\nFOIA\nInformation Quality\nNon-Discrimination Statement\nPlain Writing\nPrivacy Policy\nUSA.gov\nUSDA.gov\nWhite House\nWorld Agricultural Outlook Board\n\n\n\n \n \n  \n\n\n\n\n\n"
        }
      ],
      "section":[
        {
          "id":"s1",
          "name":"main",
          "processed-as":"english",
          "allowed-as":[
            "english"
          ],
          "text-id":"main",
          "head":9,
          "tail":29
        },
        {
          "id":"s2",
          "name":"main",
          "processed-as":"english",
          "allowed-as":[
            "english"
          ],
          "text-id":"main",
          "head":43,
          "tail":52
        },
        {
          "id":"s3",
          "name":"main",
          "processed-as":"english",
          "allowed-as":[
            "english"
          ],
          "text-id":"main",
          "head":55,
          "tail":64
        },
        {
          "id":"s4",
          "name":"main",
          "processed-as":"english",
          "allowed-as":[
            "english"
          ],
          "text-id":"main",
          "head":65,
          "tail":75
        },
        {
          "id":"s5",
          "name":"main",
          "processed-as":"english",
          "allowed-as":[
            "english"
          ],
          "text-id":"main",
          "head":81,
          "tail":92
        },
        {
          "id":"s6",
          "name":"main",
          "processed-as":"english",
          "allowed-as":[
            "english"
          ],
          "text-id":"main",
          "head":95,
          "tail":114
        },
        {
          "id":"s7",
          "name":"main",
          "processed-as":"english",
          "allowed-as":[
            "english"
          ],
          "text-id":"main",
          "head":134,
          "tail":207
        },
        {
          "id":"s8",
          "name":"main",
          "processed-as":"english",
          "allowed-as":[
            "english"
          ],
          "text-id":"main",
          "head":218,
          "tail":231
        },
        {
          "id":"s9",
          "name":"main",
          "processed-as":"english",
          "allowed-as":[
            "english"
          ],
          "text-id":"main",
          "head":232,
          "tail":238
        },
        {
          "id":"s10",
          "name":"main",
          "processed-as":"english",
          "allowed-as":[
            "english"
          ],
          "text-id":"main",
          "head":239,
          "tail":261
        },
        {
          "id":"s11",
          "name":"main",
          "processed-as":"english",
          "allowed-as":[
            "english"
          ],
          "text-id":"main",
          "head":262,
          "tail":281
        },
        {
          "id":"s12",
          "name":"main",
          "processed-as":"english",
          "allowed-as":[
            "english"
          ],
          "text-id":"main",
          "head":282,
          "tail":297
        },
        {
          "id":"s13",
          "name":"main",
          "processed-as":"english",
          "allowed-as":[
            "english"
          ],
          "text-id":"main",
          "head":298,
          "tail":306
        },
        {
          "id":"s14",
          "name":"main",
          "processed-as":"english",
          "allowed-as":[
            "english"
          ],
          "text-id":"main",
          "head":307,
          "tail":315
        },
        {
          "id":"s15",
          "name":"main",
          "processed-as":"english",
          "allowed-as":[
            "english"
          ],
          "text-id":"main",
          "head":349,
          "tail":411
        },
        {
          "id":"s16",
          "name":"main",
          "processed-as":"english",
          "allowed-as":[
            "english"
          ],
          "text-id":"main",
          "head":421,
          "tail":451
        },
        {
          "id":"s17",
          "name":"main",
          "processed-as":"english",
          "allowed-as":[
            "english"
          ],
          "text-id":"main",
          "head":462,
          "tail":476
        },
        {
          "id":"s18",
          "name":"main",
          "processed-as":"english",
          "allowed-as":[
            "english"
          ],
          "text-id":"main",
          "head":483,
          "tail":504
        },
        {
          "id":"s19",
          "name":"main",
          "processed-as":"english",
          "allowed-as":[
            "english"
          ],
          "text-id":"main",
          "head":519,
          "tail":530
        },
        {
          "id":"s20",
          "name":"main",
          "processed-as":"english",
          "allowed-as":[
            "english"
          ],
          "text-id":"main",
          "head":534,
          "tail":574
        },
        {
          "id":"s21",
          "name":"main",
          "processed-as":"english",
          "allowed-as":[
            "english"
          ],
          "text-id":"main",
          "head":588,
          "tail":597
        },
        {
          "id":"s22",
          "name":"main",
          "processed-as":"english",
          "allowed-as":[
            "english"
          ],
          "text-id":"main",
          "head":601,
          "tail":628
        },
        {
          "id":"s23",
          "name":"main",
          "processed-as":"english",
          "allowed-as":[
            "english"
          ],
          "text-id":"main",
          "head":636,
          "tail":1091
        },
        {
          "id":"s24",
          "name":"main",
          "processed-as":"english",
          "allowed-as":[
            "english"
          ],
          "text-id":"main",
          "head":1104,
          "tail":1111
        },
        {
          "id":"s25",
          "name":"main",
          "processed-as":"english",
          "allowed-as":[
            "english"
          ],
          "text-id":"main",
          "head":1126,
          "tail":1162
        },
        {
          "id":"s26",
          "name":"main",
          "processed-as":"english",
          "allowed-as":[
            "english"
          ],
          "text-id":"main",
          "head":1171,
          "tail":1192
        },
        {
          "id":"s27",
          "name":"main",
          "processed-as":"english",
          "allowed-as":[
            "english"
          ],
          "text-id":"main",
          "head":1209,
          "tail":1237
        },
        {
          "id":"s28",
          "name":"main",
          "processed-as":"english",
          "allowed-as":[
            "english"
          ],
          "text-id":"main",
          "head":1247,
          "tail":1500
        },
        {
          "id":"s29",
          "name":"main",
          "processed-as":"english",
          "allowed-as":[
            "english"
          ],
          "text-id":"main",
          "head":1504,
          "tail":1662
        },
        {
          "id":"s30",
          "name":"main",
          "processed-as":"english",
          "allowed-as":[
            "english"
          ],
          "text-id":"main",
          "head":1667,
          "tail":1692
        },
        {
          "id":"s31",
          "name":"main",
          "processed-as":"english",
          "allowed-as":[
            "english"
          ],
          "text-id":"main",
          "head":1701,
          "tail":1804
        },
        {
          "id":"s32",
          "name":"main",
          "processed-as":"english",
          "allowed-as":[
            "english"
          ],
          "text-id":"main",
          "head":1822,
          "tail":1836
        },
        {
          "id":"s33",
          "name":"main",
          "processed-as":"english",
          "allowed-as":[
            "english"
          ],
          "text-id":"main",
          "head":1838,
          "tail":1845
        },
        {
          "id":"s34",
          "name":"main",
          "processed-as":"english",
          "allowed-as":[
            "english"
          ],
          "text-id":"main",
          "head":1846,
          "tail":1857
        },
        {
          "id":"s35",
          "name":"main",
          "processed-as":"english",
          "allowed-as":[
            "english"
          ],
          "text-id":"main",
          "head":1858,
          "tail":1861
        },
        {
          "id":"s36",
          "name":"main",
          "processed-as":"english",
          "allowed-as":[
            "english"
          ],
          "text-id":"main",
          "head":1862,
          "tail":1870
        },
        {
          "id":"s37",
          "name":"main",
          "processed-as":"english",
          "allowed-as":[
            "english"
          ],
          "text-id":"main",
          "head":1871,
          "tail":1878
        },
        {
          "id":"s38",
          "name":"main",
          "processed-as":"english",
          "allowed-as":[
            "english"
          ],
          "text-id":"main",
          "head":1879,
          "tail":1885
        },
        {
          "id":"s39",
          "name":"main",
          "processed-as":"english",
          "allowed-as":[
            "english"
          ],
          "text-id":"main",
          "head":1891,
          "tail":1905
        },
        {
          "id":"s40",
          "name":"main",
          "processed-as":"english",
          "allowed-as":[
            "english"
          ],
          "text-id":"main",
          "head":1907,
          "tail":1931
        },
        {
          "id":"s41",
          "name":"main",
          "processed-as":"english",
          "allowed-as":[
            "english"
          ],
          "text-id":"main",
          "head":1936,
          "tail":1953
        },
        {
          "id":"s42",
          "name":"main",
          "processed-as":"english",
          "allowed-as":[
            "english"
          ],
          "text-id":"main",
          "head":1973,
          "tail":1993
        },
        {
          "id":"s43",
          "name":"main",
          "processed-as":"english",
          "allowed-as":[
            "english"
          ],
          "text-id":"main",
          "head":1994,
          "tail":2017
        },
        {
          "id":"s44",
          "name":"main",
          "processed-as":"english",
          "allowed-as":[
            "english"
          ],
          "text-id":"main",
          "head":2018,
          "tail":2043
        },
        {
          "id":"s45",
          "name":"main",
          "processed-as":"english",
          "allowed-as":[
            "english"
          ],
          "text-id":"main",
          "head":2044,
          "tail":2048
        },
        {
          "id":"s46",
          "name":"main",
          "processed-as":"english",
          "allowed-as":[
            "english"
          ],
          "text-id":"main",
          "head":2049,
          "tail":2068
        },
        {
          "id":"s47",
          "name":"main",
          "processed-as":"english",
          "allowed-as":[
            "english"
          ],
          "text-id":"main",
          "head":2069,
          "tail":2097
        },
        {
          "id":"s48",
          "name":"main",
          "processed-as":"english",
          "allowed-as":[
            "english"
          ],
          "text-id":"main",
          "head":2098,
          "tail":2111
        },
        {
          "id":"s49",
          "name":"main",
          "processed-as":"english",
          "allowed-as":[
            "english"
          ],
          "text-id":"main",
          "head":2112,
          "tail":2126
        },
        {
          "id":"s50",
          "name":"main",
          "processed-as":"english",
          "allowed-as":[
            "english"
          ],
          "text-id":"main",
          "head":2127,
          "tail":2134
        },
        {
          "id":"s51",
          "name":"main",
          "processed-as":"english",
          "allowed-as":[
            "english"
          ],
          "text-id":"main",
          "head":2135,
          "tail":2143
        },
        {
          "id":"s52",
          "name":"main",
          "processed-as":"english",
          "allowed-as":[
            "english"
          ],
          "text-id":"main",
          "head":2144,
          "tail":2155
        },
        {
          "id":"s53",
          "name":"main",
          "processed-as":"english",
          "allowed-as":[
            "english"
          ],
          "text-id":"main",
          "head":2156,
          "tail":2188
        }
      ],
      "entity":[
        {
          "ontology":"entity:concept:social_media:username",
          "value":"@USDAForeignAg",
          "id":"id1",
          "value-type":"name",
          "resolve":"usdaforeignag",
          "value-rank":50,
          "entity-value":[
            {
              "type":"name",
              "value":"@USDAForeignAg",
              "script":"latin"
            }
          ],
          "entity-mention":[
            {
              "type":"name",
              "value":"@USDAForeignAg",
              "section":"main",
              "section-id":"s40",
              "text-id":"main",
              "head":1917,
              "tail":1931
            }
          ]
        },
        {
          "ontology":"entity:numeric:money",
          "value":"nearly $40 billion",
          "id":"id3",
          "value-type":"name",
          "resolve":"usd_40000000000",
          "value-rank":50,
          "entity-value":[
            {
              "type":"name",
              "value":"nearly $40 billion",
              "script":"latin"
            }
          ],
          "property":[
            {
              "name":"mod",
              "value":"less_than"
            },
            {
              "name":"norm",
              "value":"40000000000"
            },
            {
              "name":"currency",
              "value":"usd"
            }
          ],
          "entity-mention":[
            {
              "type":"name",
              "value":"nearly $40 billion",
              "section":"main",
              "section-id":"s28",
              "text-id":"main",
              "head":1435,
              "tail":1453,
              "property":[
                {
                  "name":"mod",
                  "value":"less_than"
                },
                {
                  "name":"norm",
                  "value":"40000000000"
                },
                {
                  "name":"currency",
                  "value":"usd"
                }
              ],
              "score":[
                {
                  "type":"confidence",
                  "value":4
                }
              ]
            }
          ]
        },
        {
          "ontology":"entity:organization:company",
          "value":"Economic Research Service",
          "norm":"Economic Research Service",
          "id":"id5",
          "value-type":"name",
          "resolve":"economic_research_service",
          "value-rank":50,
          "entity-value":[
            {
              "type":"name",
              "value":"Economic Research Service",
              "script":"latin"
            }
          ],
          "property":[
            {
              "name":"industry",
              "value":"other"
            }
          ],
          "entity-mention":[
            {
              "type":"name",
              "value":"Economic Research Service",
              "section":"main",
              "section-id":"s44",
              "text-id":"main",
              "head":2018,
              "tail":2043,
              "property":[
                {
                  "name":"industry",
                  "value":"other"
                }
              ],
              "score":[
                {
                  "type":"confidence",
                  "value":3
                }
              ]
            }
          ]
        },
        {
          "ontology":"entity:organization:company",
          "value":"Facebook",
          "norm":"Facebook",
          "id":"id7",
          "value-type":"name",
          "resolve":"facebook",
          "value-rank":50,
          "entity-value":[
            {
              "type":"name",
              "value":"Facebook",
              "script":"latin"
            }
          ],
          "property":[
            {
              "name":"industry",
              "value":"social media"
            }
          ],
          "entity-mention":[
            {
              "type":"name",
              "value":"Facebook",
              "section":"main",
              "section-id":"s36",
              "text-id":"main",
              "head":1862,
              "tail":1870,
              "property":[
                {
                  "name":"industry",
                  "value":"social media"
                }
              ],
              "score":[
                {
                  "type":"confidence",
                  "value":4
                }
              ]
            }
          ]
        },
        {
          "ontology":"entity:organization:company",
          "value":"Flickr",
          "norm":"Flickr",
          "id":"id9",
          "value-type":"name",
          "resolve":"flickr",
          "value-rank":50,
          "entity-value":[
            {
              "type":"name",
              "value":"Flickr",
              "script":"latin"
            }
          ],
          "property":[
            {
              "name":"industry",
              "value":"social media"
            }
          ],
          "entity-mention":[
            {
              "type":"name",
              "value":"Flickr",
              "section":"main",
              "section-id":"s38",
              "text-id":"main",
              "head":1879,
              "tail":1885,
              "property":[
                {
                  "name":"industry",
                  "value":"social media"
                }
              ],
              "score":[
                {
                  "type":"confidence",
                  "value":4
                }
              ]
            }
          ]
        },
        {
          "ontology":"entity:organization:company",
          "value":"HomeData & AnalysisUkraine",
          "norm":"Homedata and Analysisukraine",
          "id":"id11",
          "value-type":"name",
          "resolve":"homedata_analysisukraine",
          "value-rank":50,
          "entity-value":[
            {
              "type":"name",
              "value":"HomeData & AnalysisUkraine",
              "script":"latin"
            }
          ],
          "property":[
            {
              "name":"industry",
              "value":"other"
            }
          ],
          "entity-mention":[
            {
              "type":"name",
              "value":"HomeData & AnalysisUkraine",
              "section":"main",
              "section-id":"s15",
              "text-id":"main",
              "head":362,
              "tail":388,
              "property":[
                {
                  "name":"industry",
                  "value":"other"
                }
              ],
              "score":[
                {
                  "type":"confidence",
                  "value":3
                }
              ]
            }
          ]
        },
        {
          "ontology":"entity:organization:company",
          "value":"Twitter",
          "norm":"Twitter",
          "id":"id13",
          "value-type":"name",
          "resolve":"twitter",
          "value-rank":70,
          "entity-value":[
            {
              "type":"name",
              "value":"Twitter",
              "script":"latin"
            }
          ],
          "property":[
            {
              "name":"industry",
              "value":"social media"
            }
          ],
          "entity-mention":[
            {
              "type":"name",
              "value":"Twitter",
              "section":"main",
              "section-id":"s33",
              "text-id":"main",
              "head":1838,
              "tail":1845,
              "property":[
                {
                  "name":"industry",
                  "value":"social media"
                }
              ],
              "score":[
                {
                  "type":"confidence",
                  "value":4
                }
              ]
            },
            {
              "type":"name",
              "value":"Twitter",
              "section":"main",
              "section-id":"s39",
              "text-id":"main",
              "head":1898,
              "tail":1905,
              "property":[
                {
                  "name":"industry",
                  "value":"social media"
                }
              ],
              "score":[
                {
                  "type":"confidence",
                  "value":4
                }
              ]
            }
          ]
        },
        {
          "ontology":"entity:organization:company",
          "value":"USDA United States Department of Agriculture Foreign Agricultural Service",
          "norm":"Usda United States Department of Agriculture Foreign Agricultural Service",
          "id":"id16",
          "value-type":"name",
          "resolve":"usda_united_states_department_of_agriculture_foreign_agricultural_service",
          "value-rank":50,
          "entity-value":[
            {
              "type":"name",
              "value":"USDA United States Department of Agriculture Foreign Agricultural Service",
              "script":"latin"
            },
            {
              "type":"name",
              "value":"USDA",
              "script":"latin"
            }
          ],
          "property":[
            {
              "name":"industry",
              "value":"other"
            }
          ],
          "entity-mention":[
            {
              "type":"name",
              "value":"USDA United States Department of Agriculture Foreign Agricultural Service",
              "section":"main",
              "section-id":"s7",
              "text-id":"main",
              "head":134,
              "tail":207,
              "property":[
                {
                  "name":"industry",
                  "value":"other"
                }
              ],
              "score":[
                {
                  "type":"confidence",
                  "value":3
                }
              ]
            },
            {
              "type":"name",
              "value":"USDA",
              "section":"main",
              "section-id":"s51",
              "text-id":"main",
              "head":2135,
              "tail":2139,
              "property":[
                {
                  "name":"industry",
                  "value":"other"
                }
              ],
              "score":[
                {
                  "type":"confidence",
                  "value":3
                }
              ]
            }
          ]
        },
        {
          "ontology":"entity:organization:company",
          "value":"YouTube",
          "norm":"YouTube",
          "id":"id19",
          "value-type":"name",
          "resolve":"youtube",
          "value-rank":50,
          "entity-value":[
            {
              "type":"name",
              "value":"YouTube",
              "script":"latin"
            }
          ],
          "property":[
            {
              "name":"industry",
              "value":"social media"
            }
          ],
          "entity-mention":[
            {
              "type":"name",
              "value":"YouTube",
              "section":"main",
              "section-id":"s37",
              "text-id":"main",
              "head":1871,
              "tail":1878,
              "property":[
                {
                  "name":"industry",
                  "value":"social media"
                }
              ],
              "score":[
                {
                  "type":"confidence",
                  "value":4
                }
              ]
            }
          ]
        },
        {
          "ontology":"entity:organization:government",
          "value":"White House",
          "norm":"White House (US)",
          "id":"id21",
          "value-type":"name",
          "resolve":"white_house|us",
          "value-rank":50,
          "entity-value":[
            {
              "type":"name",
              "value":"White House",
              "script":"latin"
            }
          ],
          "entity-mention":[
            {
              "type":"name",
              "value":"White House",
              "section":"main",
              "section-id":"s52",
              "text-id":"main",
              "head":2144,
              "tail":2155,
              "score":[
                {
                  "type":"confidence",
                  "value":4
                }
              ]
            }
          ]
        },
        {
          "ontology":"entity:organization:other",
          "value":"Office of Agricultural Affairs",
          "norm":"Office of Agricultural Affairs",
          "id":"id23",
          "value-type":"name",
          "resolve":"office_of_agricultural_affairs",
          "value-rank":50,
          "entity-value":[
            {
              "type":"name",
              "value":"Office of Agricultural Affairs",
              "script":"latin"
            }
          ],
          "link-ref":[
            {
              "role":"organization",
              "role-type":"source",
              "ontology":"link:organization:org_location",
              "idref":"id62",
              "entity-arg":[
                {
                  "role":"location",
                  "role-type":"target",
                  "value":"Kyiv",
                  "value-type":"name",
                  "ontology":"entity:place:city",
                  "idref":"id27",
                  "geodetic":{
                    "latitude":"50.4333",
                    "longitude":"30.5167",
                    "confidence":"1"
                  }
                }
              ]
            }
          ],
          "entity-mention":[
            {
              "type":"name",
              "value":"Office of Agricultural Affairs",
              "section":"main",
              "section-id":"s25",
              "text-id":"main",
              "head":1126,
              "tail":1156,
              "score":[
                {
                  "type":"confidence",
                  "value":3
                }
              ],
              "link-ref":[
                {
                  "role":"organization",
                  "role-type":"source",
                  "ontology":"link:organization:org_location",
                  "idref":"id62",
                  "entity-arg":[
                    {
                      "role":"location",
                      "role-type":"target",
                      "value":"Kyiv",
                      "value-type":"name",
                      "ontology":"entity:place:city",
                      "idref":"id27",
                      "entity-arg-mention":{
                        "type":"name",
                        "value":"Kyiv",
                        "section":"main",
                        "section-id":"s25",
                        "text-id":"main",
                        "head":1158,
                        "tail":1162
                      },
                      "geodetic":{
                        "latitude":"50.4333",
                        "longitude":"30.5167",
                        "confidence":"1"
                      }
                    }
                  ]
                }
              ]
            }
          ]
        },
        {
          "ontology":"entity:organization:other",
          "value":"World Agricultural Outlook Board",
          "norm":"World Agricultural Outlook Board",
          "id":"id25",
          "value-type":"name",
          "resolve":"world_agricultural_outlook_board",
          "value-rank":50,
          "entity-value":[
            {
              "type":"name",
              "value":"World Agricultural Outlook Board",
              "script":"latin"
            }
          ],
          "entity-mention":[
            {
              "type":"name",
              "value":"World Agricultural Outlook Board",
              "section":"main",
              "section-id":"s53",
              "text-id":"main",
              "head":2156,
              "tail":2188,
              "score":[
                {
                  "type":"confidence",
                  "value":3
                }
              ]
            }
          ]
        },
        {
          "ontology":"entity:place:city",
          "value":"Kyiv",
          "norm":"Kiev (Misto Kyyiv, UP)",
          "id":"id27",
          "value-type":"name",
          "resolve":"kiev|misto kyyiv|up",
          "value-rank":50,
          "entity-value":[
            {
              "type":"name",
              "value":"Kyiv",
              "script":"latin"
            }
          ],
          "property":[
            {
              "name":"fips_10_4_country",
              "value":"up"
            },
            {
              "name":"iso_3166_1_country",
              "value":"ua"
            },
            {
              "name":"country",
              "value":"ukraine"
            },
            {
              "name":"province",
              "value":"misto kyyiv"
            }
          ],
          "geodetic":{
            "latitude":"50.4333",
            "longitude":"30.5167",
            "confidence":"1",
            "property":[
              {
                "name":"city",
                "value":"Kiev"
              },
              {
                "name":"province",
                "value":"Misto Kyyiv"
              },
              {
                "name":"country",
                "value":"UP"
              }
            ]
          },
          "link-ref":[
            {
              "role":"location",
              "role-type":"target",
              "ontology":"link:organization:org_location",
              "idref":"id62",
              "entity-arg":[
                {
                  "role":"organization",
                  "role-type":"source",
                  "value":"Office of Agricultural Affairs",
                  "value-type":"name",
                  "ontology":"entity:organization:other",
                  "idref":"id23"
                }
              ]
            }
          ],
          "entity-mention":[
            {
              "type":"name",
              "value":"Kyiv",
              "section":"main",
              "section-id":"s25",
              "text-id":"main",
              "head":1158,
              "tail":1162,
              "property":[
                {
                  "name":"fips_10_4_country",
                  "value":"up"
                },
                {
                  "name":"iso_3166_1_country",
                  "value":"ua"
                },
                {
                  "name":"country",
                  "value":"ukraine"
                },
                {
                  "name":"province",
                  "value":"misto kyyiv"
                }
              ],
              "score":[
                {
                  "type":"confidence",
                  "value":4
                }
              ],
              "geodetic":{
                "latitude":"50.4333",
                "longitude":"30.5167",
                "confidence":"1",
                "property":[
                  {
                    "name":"city",
                    "value":"Kiev"
                  },
                  {
                    "name":"province",
                    "value":"Misto Kyyiv"
                  },
                  {
                    "name":"country",
                    "value":"UP"
                  }
                ]
              },
              "link-ref":[
                {
                  "role":"location",
                  "role-type":"target",
                  "ontology":"link:organization:org_location",
                  "idref":"id62",
                  "entity-arg":[
                    {
                      "role":"organization",
                      "role-type":"source",
                      "value":"Office of Agricultural Affairs",
                      "value-type":"name",
                      "ontology":"entity:organization:other",
                      "idref":"id23",
                      "entity-arg-mention":{
                        "type":"name",
                        "value":"Office of Agricultural Affairs",
                        "section":"main",
                        "section-id":"s25",
                        "text-id":"main",
                        "head":1126,
                        "tail":1156
                      }
                    }
                  ]
                }
              ]
            }
          ]
        },
        {
          "ontology":"entity:place:continent",
          "value":"Eurasia",
          "norm":"Eurasia",
          "id":"id29",
          "value-type":"name",
          "resolve":"eurasia",
          "value-rank":50,
          "entity-value":[
            {
              "type":"name",
              "value":"Eurasia",
              "script":"latin"
            }
          ],
          "entity-mention":[
            {
              "type":"name",
              "value":"Eurasia",
              "section":"main",
              "section-id":"s22",
              "text-id":"main",
              "head":612,
              "tail":619,
              "score":[
                {
                  "type":"confidence",
                  "value":4
                }
              ]
            }
          ]
        },
        {
          "ontology":"entity:place:continent",
          "value":"Europe",
          "norm":"Europe",
          "id":"id31",
          "value-type":"name",
          "resolve":"europe",
          "value-rank":50,
          "entity-value":[
            {
              "type":"name",
              "value":"Europe",
              "script":"latin"
            }
          ],
          "entity-mention":[
            {
              "type":"name",
              "value":"Europe",
              "section":"main",
              "section-id":"s22",
              "text-id":"main",
              "head":601,
              "tail":607,
              "score":[
                {
                  "type":"confidence",
                  "value":4
                }
              ]
            }
          ]
        },
        {
          "ontology":"entity:place:continent",
          "value":"North American",
          "norm":"North America",
          "id":"id33",
          "value-type":"name",
          "resolve":"north_america",
          "value-rank":20,
          "entity-value":[
            {
              "type":"name",
              "value":"North American",
              "implies":"North America",
              "script":"latin"
            }
          ],
          "entity-mention":[
            {
              "type":"name",
              "value":"North American",
              "implies":"North America",
              "section":"main",
              "section-id":"s28",
              "text-id":"main",
              "head":1296,
              "tail":1310
            }
          ]
        },
        {
          "ontology":"entity:place:country",
          "value":"Canada",
          "norm":"Canada",
          "id":"id35",
          "value-type":"name",
          "resolve":"ca",
          "value-rank":50,
          "entity-value":[
            {
              "type":"name",
              "value":"Canada",
              "script":"latin"
            }
          ],
          "property":[
            {
              "name":"fips_10_4_country",
              "value":"ca"
            },
            {
              "name":"iso_3166_1_country",
              "value":"ca"
            },
            {
              "name":"country",
              "value":"canada"
            }
          ],
          "geodetic":{
            "latitude":"60",
            "longitude":"-95",
            "confidence":"1",
            "property":[
              {
                "name":"country",
                "value":"CA"
              }
            ]
          },
          "entity-mention":[
            {
              "type":"name",
              "value":"Canada",
              "section":"main",
              "section-id":"s28",
              "text-id":"main",
              "head":1408,
              "tail":1414,
              "property":[
                {
                  "name":"fips_10_4_country",
                  "value":"ca"
                },
                {
                  "name":"iso_3166_1_country",
                  "value":"ca"
                },
                {
                  "name":"country",
                  "value":"canada"
                }
              ],
              "score":[
                {
                  "type":"confidence",
                  "value":4
                }
              ],
              "geodetic":{
                "latitude":"60",
                "longitude":"-95",
                "confidence":"1",
                "property":[
                  {
                    "name":"country",
                    "value":"CA"
                  }
                ]
              }
            }
          ]
        },
        {
          "ontology":"entity:place:country",
          "value":"Mexico",
          "norm":"Mexico",
          "id":"id37",
          "value-type":"name",
          "resolve":"mx",
          "value-rank":50,
          "entity-value":[
            {
              "type":"name",
              "value":"Mexico",
              "script":"latin"
            }
          ],
          "property":[
            {
              "name":"fips_10_4_country",
              "value":"mx"
            },
            {
              "name":"iso_3166_1_country",
              "value":"mx"
            },
            {
              "name":"country",
              "value":"mexico"
            }
          ],
          "geodetic":{
            "latitude":"23",
            "longitude":"-102",
            "confidence":"1",
            "property":[
              {
                "name":"country",
                "value":"MX"
              }
            ]
          },
          "entity-mention":[
            {
              "type":"name",
              "value":"Mexico",
              "section":"main",
              "section-id":"s28",
              "text-id":"main",
              "head":1397,
              "tail":1403,
              "property":[
                {
                  "name":"fips_10_4_country",
                  "value":"mx"
                },
                {
                  "name":"iso_3166_1_country",
                  "value":"mx"
                },
                {
                  "name":"country",
                  "value":"mexico"
                }
              ],
              "score":[
                {
                  "type":"confidence",
                  "value":4
                }
              ],
              "geodetic":{
                "latitude":"23",
                "longitude":"-102",
                "confidence":"1",
                "property":[
                  {
                    "name":"country",
                    "value":"MX"
                  }
                ]
              }
            }
          ]
        },
        {
          "ontology":"entity:place:country",
          "value":"U.S.",
          "norm":"United States",
          "id":"id39",
          "value-type":"name",
          "resolve":"us",
          "value-rank":70,
          "entity-value":[
            {
              "type":"name",
              "value":"U.S.",
              "script":"latin"
            },
            {
              "type":"name",
              "value":"USA",
              "script":"latin"
            }
          ],
          "property":[
            {
              "name":"fips_10_4_country",
              "value":"us"
            },
            {
              "name":"iso_3166_1_country",
              "value":"us"
            },
            {
              "name":"country",
              "value":"united states"
            }
          ],
          "geodetic":{
            "latitude":"38",
            "longitude":"-97",
            "confidence":"1",
            "property":[
              {
                "name":"country",
                "value":"US"
              }
            ]
          },
          "entity-mention":[
            {
              "type":"name",
              "value":"U.S.",
              "section":"main",
              "section-id":"s28",
              "text-id":"main",
              "head":1391,
              "tail":1395,
              "property":[
                {
                  "name":"fips_10_4_country",
                  "value":"us"
                },
                {
                  "name":"iso_3166_1_country",
                  "value":"us"
                },
                {
                  "name":"country",
                  "value":"united states"
                }
              ],
              "score":[
                {
                  "type":"confidence",
                  "value":4
                }
              ],
              "geodetic":{
                "latitude":"38",
                "longitude":"-97",
                "confidence":"1",
                "property":[
                  {
                    "name":"country",
                    "value":"US"
                  }
                ]
              }
            },
            {
              "type":"name",
              "value":"U.S.",
              "section":"main",
              "section-id":"s28",
              "text-id":"main",
              "head":1421,
              "tail":1425,
              "property":[
                {
                  "name":"fips_10_4_country",
                  "value":"us"
                },
                {
                  "name":"iso_3166_1_country",
                  "value":"us"
                },
                {
                  "name":"country",
                  "value":"united states"
                }
              ],
              "score":[
                {
                  "type":"confidence",
                  "value":4
                }
              ],
              "geodetic":{
                "latitude":"38",
                "longitude":"-97",
                "confidence":"1",
                "property":[
                  {
                    "name":"country",
                    "value":"US"
                  }
                ]
              }
            },
            {
              "type":"name",
              "value":"USA",
              "section":"main",
              "section-id":"s50",
              "text-id":"main",
              "head":2127,
              "tail":2130,
              "property":[
                {
                  "name":"fips_10_4_country",
                  "value":"us"
                },
                {
                  "name":"iso_3166_1_country",
                  "value":"us"
                },
                {
                  "name":"country",
                  "value":"united states"
                }
              ],
              "score":[
                {
                  "type":"confidence",
                  "value":4
                }
              ],
              "geodetic":{
                "latitude":"38",
                "longitude":"-97",
                "confidence":"1",
                "property":[
                  {
                    "name":"country",
                    "value":"US"
                  }
                ]
              }
            }
          ]
        },
        {
          "ontology":"entity:place:country",
          "value":"Ukraine",
          "norm":"Ukraine",
          "id":"id43",
          "value-type":"name",
          "resolve":"up",
          "value-rank":50,
          "entity-value":[
            {
              "type":"name",
              "value":"Ukraine",
              "script":"latin"
            }
          ],
          "property":[
            {
              "name":"fips_10_4_country",
              "value":"up"
            },
            {
              "name":"iso_3166_1_country",
              "value":"ua"
            },
            {
              "name":"country",
              "value":"ukraine"
            }
          ],
          "geodetic":{
            "latitude":"49",
            "longitude":"32",
            "confidence":"1",
            "property":[
              {
                "name":"country",
                "value":"UP"
              }
            ]
          },
          "entity-mention":[
            {
              "type":"name",
              "value":"Ukraine",
              "section":"main",
              "section-id":"s16",
              "text-id":"main",
              "head":421,
              "tail":428,
              "property":[
                {
                  "name":"fips_10_4_country",
                  "value":"up"
                },
                {
                  "name":"iso_3166_1_country",
                  "value":"ua"
                },
                {
                  "name":"country",
                  "value":"ukraine"
                }
              ],
              "score":[
                {
                  "type":"confidence",
                  "value":4
                }
              ],
              "geodetic":{
                "latitude":"49",
                "longitude":"32",
                "confidence":"1",
                "property":[
                  {
                    "name":"country",
                    "value":"UP"
                  }
                ]
              }
            },
            {
              "type":"name",
              "value":"Ukraine",
              "section":"main",
              "section-id":"s22",
              "text-id":"main",
              "head":621,
              "tail":628,
              "property":[
                {
                  "name":"fips_10_4_country",
                  "value":"up"
                },
                {
                  "name":"iso_3166_1_country",
                  "value":"ua"
                },
                {
                  "name":"country",
                  "value":"ukraine"
                }
              ],
              "score":[
                {
                  "type":"confidence",
                  "value":4
                }
              ],
              "geodetic":{
                "latitude":"49",
                "longitude":"32",
                "confidence":"1",
                "property":[
                  {
                    "name":"country",
                    "value":"UP"
                  }
                ]
              }
            },
            {
              "type":"name",
              "value":"Ukraine",
              "section":"main",
              "section-id":"s23",
              "text-id":"main",
              "head":892,
              "tail":899,
              "property":[
                {
                  "name":"fips_10_4_country",
                  "value":"up"
                },
                {
                  "name":"iso_3166_1_country",
                  "value":"ua"
                },
                {
                  "name":"country",
                  "value":"ukraine"
                }
              ],
              "score":[
                {
                  "type":"confidence",
                  "value":4
                }
              ],
              "geodetic":{
                "latitude":"49",
                "longitude":"32",
                "confidence":"1",
                "property":[
                  {
                    "name":"country",
                    "value":"UP"
                  }
                ]
              }
            },
            {
              "type":"name",
              "value":"Ukraine",
              "section":"main",
              "section-id":"s23",
              "text-id":"main",
              "head":1061,
              "tail":1068,
              "property":[
                {
                  "name":"fips_10_4_country",
                  "value":"up"
                },
                {
                  "name":"iso_3166_1_country",
                  "value":"ua"
                },
                {
                  "name":"country",
                  "value":"ukraine"
                }
              ],
              "score":[
                {
                  "type":"confidence",
                  "value":4
                }
              ],
              "geodetic":{
                "latitude":"49",
                "longitude":"32",
                "confidence":"1",
                "property":[
                  {
                    "name":"country",
                    "value":"UP"
                  }
                ]
              }
            },
            {
              "type":"name",
              "value":"Ukraine",
              "section":"main",
              "section-id":"s29",
              "text-id":"main",
              "head":1504,
              "tail":1511,
              "property":[
                {
                  "name":"fips_10_4_country",
                  "value":"up"
                },
                {
                  "name":"iso_3166_1_country",
                  "value":"ua"
                },
                {
                  "name":"country",
                  "value":"ukraine"
                }
              ],
              "score":[
                {
                  "type":"confidence",
                  "value":4
                }
              ],
              "geodetic":{
                "latitude":"49",
                "longitude":"32",
                "confidence":"1",
                "property":[
                  {
                    "name":"country",
                    "value":"UP"
                  }
                ]
              }
            }
          ]
        },
        {
          "ontology":"entity:place:water",
          "value":"Black Sea",
          "norm":"Black Sea",
          "id":"id49",
          "value-type":"name",
          "resolve":"black_sea",
          "value-rank":50,
          "entity-value":[
            {
              "type":"name",
              "value":"Black Sea",
              "script":"latin"
            }
          ],
          "entity-mention":[
            {
              "type":"name",
              "value":"Black Sea",
              "section":"main",
              "section-id":"s23",
              "text-id":"main",
              "head":942,
              "tail":951,
              "score":[
                {
                  "type":"confidence",
                  "value":3
                }
              ]
            }
          ]
        },
        {
          "ontology":"entity:time:date",
          "value":"2018",
          "id":"id51",
          "value-type":"name",
          "resolve":"2018",
          "value-rank":50,
          "entity-value":[
            {
              "type":"name",
              "value":"2018",
              "script":"latin"
            }
          ],
          "property":[
            {
              "name":"year",
              "value":"2018"
            }
          ],
          "entity-mention":[
            {
              "type":"name",
              "value":"2018",
              "section":"main",
              "section-id":"s28",
              "text-id":"main",
              "head":1495,
              "tail":1499,
              "property":[
                {
                  "name":"year",
                  "value":"2018"
                }
              ],
              "score":[
                {
                  "type":"confidence",
                  "value":4
                }
              ]
            }
          ]
        },
        {
          "ontology":"entity:time:date",
          "value":"2019",
          "id":"id53",
          "value-type":"name",
          "resolve":"2019",
          "value-rank":50,
          "entity-value":[
            {
              "type":"name",
              "value":"2019",
              "script":"latin"
            }
          ],
          "property":[
            {
              "name":"year",
              "value":"2019"
            }
          ],
          "entity-mention":[
            {
              "type":"name",
              "value":"2019",
              "section":"main",
              "section-id":"s28",
              "text-id":"main",
              "head":1329,
              "tail":1333,
              "property":[
                {
                  "name":"year",
                  "value":"2019"
                }
              ],
              "score":[
                {
                  "type":"confidence",
                  "value":4
                }
              ]
            },
            {
              "type":"name",
              "value":"2019",
              "section":"main",
              "section-id":"s29",
              "text-id":"main",
              "head":1543,
              "tail":1547,
              "property":[
                {
                  "name":"year",
                  "value":"2019"
                }
              ],
              "score":[
                {
                  "type":"confidence",
                  "value":4
                }
              ]
            }
          ]
        },
        {
          "ontology":"entity:time:date",
          "value":"April 19, 2018",
          "id":"id56",
          "value-type":"name",
          "resolve":"2018_04_19",
          "value-rank":50,
          "entity-value":[
            {
              "type":"name",
              "value":"April 19, 2018",
              "script":"latin"
            }
          ],
          "property":[
            {
              "name":"day",
              "value":"19"
            },
            {
              "name":"month",
              "value":"04"
            },
            {
              "name":"year",
              "value":"2018"
            }
          ],
          "entity-mention":[
            {
              "type":"name",
              "value":"April 19, 2018",
              "section":"main",
              "section-id":"s17",
              "text-id":"main",
              "head":462,
              "tail":476,
              "property":[
                {
                  "name":"day",
                  "value":"19"
                },
                {
                  "name":"month",
                  "value":"04"
                },
                {
                  "name":"year",
                  "value":"2018"
                }
              ],
              "score":[
                {
                  "type":"confidence",
                  "value":4
                }
              ]
            }
          ]
        },
        {
          "ontology":"entity:time:date",
          "value":"summer",
          "id":"id58",
          "value-type":"name",
          "resolve":"summer",
          "value-rank":50,
          "entity-value":[
            {
              "type":"name",
              "value":"summer",
              "script":"latin"
            }
          ],
          "property":[
            {
              "name":"season",
              "value":"summer"
            }
          ],
          "entity-mention":[
            {
              "type":"name",
              "value":"summer",
              "section":"main",
              "section-id":"s23",
              "text-id":"main",
              "head":845,
              "tail":851,
              "property":[
                {
                  "name":"season",
                  "value":"summer"
                }
              ],
              "score":[
                {
                  "type":"confidence",
                  "value":4
                }
              ]
            }
          ]
        },
        {
          "ontology":"entity:time:temporal",
          "value":"the fourth year",
          "id":"id60",
          "value-type":"name",
          "entity-value":[
            {
              "type":"name",
              "value":"the fourth year",
              "script":"latin"
            }
          ],
          "entity-mention":[
            {
              "type":"name",
              "value":"the fourth year",
              "section":"main",
              "section-id":"s23",
              "text-id":"main",
              "head":1035,
              "tail":1050,
              "score":[
                {
                  "type":"confidence",
                  "value":4
                }
              ]
            }
          ]
        }
      ],
      "link":[
        {
          "ontology":"link:organization:org_location",
          "id":"id62",
          "entity-arg":[
            {
              "role":"organization",
              "role-type":"source",
              "value":"Office of Agricultural Affairs",
              "value-type":"name",
              "ontology":"entity:organization:other",
              "idref":"id23"
            },
            {
              "role":"location",
              "role-type":"target",
              "value":"Kyiv",
              "value-type":"name",
              "ontology":"entity:place:city",
              "idref":"id27",
              "geodetic":{
                "latitude":"50.4333",
                "longitude":"30.5167",
                "confidence":"1"
              }
            }
          ],
          "link-mention":[
            {
              "entity-arg":[
                {
                  "role":"organization",
                  "role-type":"source",
                  "value":"Office of Agricultural Affairs",
                  "value-type":"name",
                  "ontology":"entity:organization:other",
                  "idref":"id23",
                  "entity-arg-mention":{
                    "type":"name",
                    "value":"Office of Agricultural Affairs",
                    "section":"main",
                    "section-id":"s25",
                    "text-id":"main",
                    "head":1126,
                    "tail":1156
                  }
                },
                {
                  "role":"location",
                  "role-type":"target",
                  "value":"Kyiv",
                  "value-type":"name",
                  "ontology":"entity:place:city",
                  "idref":"id27",
                  "entity-arg-mention":{
                    "type":"name",
                    "value":"Kyiv",
                    "section":"main",
                    "section-id":"s25",
                    "text-id":"main",
                    "head":1158,
                    "tail":1162
                  },
                  "geodetic":{
                    "latitude":"50.4333",
                    "longitude":"30.5167",
                    "confidence":"1"
                  }
                }
              ]
            }
          ]
        }
      ]
    }
  ]
}